{
  "snapshotVersion": 1,
  "kind": "preflight-summary",
  "generatedAt": "2026-07-19 22:57:58",
  "runId": "20260719-223923",
  "quick": false,
  "forcePlatformAudit": true,
  "forceSlowChecks": true,
  "pass": true,
  "failureCount": 0,
  "failedKeys": [],
  "slowReuseCount": 0,
  "slowReuseKeys": [],
  "recordsCount": 52,
  "passedCount": 52,
  "totalSeconds": 1045,
  "slowestKey": "platform-audit",
  "slowestSeconds": 549.1,
  "postCheckCount": 3,
  "postChecksPassedCount": 3,
  "postCheckFailures": [],
  "sourcePath": "output/preflight/history/20260719-223923/preflight-summary.json",
  "sourceHash": "f010c13c9eb05f356d6e174c4c084c8abbddf434957b3c1bfe8a3051dd7f5375"
}
