{
  "snapshotVersion": 1,
  "kind": "preflight-summary",
  "generatedAt": "2026-07-18 00:32:05",
  "runId": "20260718-001431",
  "quick": false,
  "forcePlatformAudit": true,
  "forceSlowChecks": true,
  "pass": true,
  "failureCount": 0,
  "failedKeys": [],
  "slowReuseCount": 0,
  "slowReuseKeys": [],
  "recordsCount": 52,
  "passedCount": 52,
  "totalSeconds": 984.4,
  "slowestKey": "platform-audit",
  "slowestSeconds": 520.4,
  "postCheckCount": 3,
  "postChecksPassedCount": 3,
  "postCheckFailures": [],
  "sourcePath": "output/preflight/history/20260718-001431/preflight-summary.json",
  "sourceHash": "d42f2f15dc0b276ce1b358894b50373725853e00d978fd1cac92400560809b27"
}
